codify/__init__.py
codify/ceasar_cyphers.py
codify/qr_coding.py
codify/util.py
codify-0.0.8.dist-info/LICENSE
codify-0.0.8.dist-info/METADATA
codify-0.0.8.dist-info/WHEEL
codify-0.0.8.dist-info/top_level.txt
codify-0.0.8.dist-info/RECORD
