Metadata-Version: 2.1
Name: codify
Version: 0.0.8
Summary: Generate codes
Home-page: https://github.com/thorwhalen/codify
Author: Thor Whalen
License: mit
Platform: any
License-File: LICENSE
Requires-Dist: qrcode
Requires-Dist: lexis
Requires-Dist: idiom
